ribasim_api/__init__.py
ribasim_api/py.typed
ribasim_api/ribasim_api.py
ribasim_api-2025.5.0.dist-info/METADATA
ribasim_api-2025.5.0.dist-info/WHEEL
ribasim_api-2025.5.0.dist-info/licenses/LICENSE
ribasim_api-2025.5.0.dist-info/RECORD
