Metadata-Version: 2.4
Name: ribasim_api
Version: 2025.5.0
Summary: Python bindings for libribasim
Project-URL: Documentation, https://ribasim.org/
Project-URL: Source, https://github.com/Deltares/Ribasim
Author-email: Deltares and contributors <ribasim.info@deltares.nl>
License: MIT
License-File: LICENSE
Classifier: Intended Audience :: Science/Research
Classifier: Topic :: Scientific/Engineering :: Hydrology
Requires-Python: >=3.11
Requires-Dist: xmipy>=1.3
Provides-Extra: tests
Requires-Dist: pytest; extra == 'tests'
Requires-Dist: ribasim; extra == 'tests'
Requires-Dist: ribasim-testmodels; extra == 'tests'
